{"inputs":{"empty-module:@remix-run/react":{"bytes":20,"imports":[],"format":"cjs"},"empty-module:react":{"bytes":20,"imports":[],"format":"cjs"},"empty-module:react-dom/client":{"bytes":20,"imports":[],"format":"cjs"},"empty-module:react/jsx-dev-runtime":{"bytes":20,"imports":[],"format":"cjs"},"app/entry.client.jsx":{"bytes":574,"imports":[{"path":"empty-module:@remix-run/react","kind":"import-statement","original":"@remix-run/react"},{"path":"empty-module:react","kind":"import-statement","original":"react"},{"path":"empty-module:react-dom/client","kind":"import-statement","original":"react-dom/client"},{"path":"empty-module:react/jsx-dev-runtime","kind":"import-statement","original":"react/jsx-dev-runtime"}],"format":"esm"},"empty-module:@remix-run/css-bundle":{"bytes":20,"imports":[],"format":"cjs"},"empty-module:@remix-run/node":{"bytes":20,"imports":[],"format":"cjs"},"empty-module:~/session.server":{"bytes":20,"imports":[],"format":"cjs"},"app/tailwind.css":{"bytes":15532,"imports":[]},"app/root.jsx":{"bytes":946,"imports":[{"path":"empty-module:@remix-run/css-bundle","kind":"import-statement","original":"@remix-run/css-bundle"},{"path":"empty-module:@remix-run/node","kind":"import-statement","original":"@remix-run/node"},{"path":"empty-module:@remix-run/react","kind":"import-statement","original":"@remix-run/react"},{"path":"empty-module:~/session.server","kind":"import-statement","original":"~/session.server"},{"path":"app/tailwind.css","kind":"import-statement","original":"~/tailwind.css"},{"path":"empty-module:react/jsx-dev-runtime","kind":"import-statement","original":"react/jsx-dev-runtime"}],"format":"esm"},"node_modules/tiny-invariant/dist/esm/tiny-invariant.js":{"bytes":452,"imports":[],"format":"esm"},"empty-module:~/models/note.server":{"bytes":20,"imports":[],"format":"cjs"},"app/routes/notes.$noteId.jsx":{"bytes":1734,"imports":[{"path":"empty-module:@remix-run/node","kind":"import-statement","original":"@remix-run/node"},{"path":"empty-module:@remix-run/react","kind":"import-statement","original":"@remix-run/react"},{"path":"node_modules/tiny-invariant/dist/esm/tiny-invariant.js","kind":"import-statement","original":"tiny-invariant"},{"path":"empty-module:~/models/note.server","kind":"import-statement","original":"~/models/note.server"},{"path":"empty-module:~/session.server","kind":"import-statement","original":"~/session.server"},{"path":"empty-module:react/jsx-dev-runtime","kind":"import-statement","original":"react/jsx-dev-runtime"}],"format":"esm"},"app/routes/notes._index.jsx":{"bytes":277,"imports":[{"path":"empty-module:@remix-run/react","kind":"import-statement","original":"@remix-run/react"},{"path":"empty-module:react/jsx-dev-runtime","kind":"import-statement","original":"react/jsx-dev-runtime"}],"format":"esm"},"empty-module:~/db.server":{"bytes":20,"imports":[],"format":"cjs"},"app/routes/healthcheck.jsx":{"bytes":775,"imports":[{"path":"empty-module:~/db.server","kind":"import-statement","original":"~/db.server"}],"format":"esm"},"app/routes/notes.new.jsx":{"bytes":3017,"imports":[{"path":"empty-module:@remix-run/node","kind":"import-statement","original":"@remix-run/node"},{"path":"empty-module:@remix-run/react","kind":"import-statement","original":"@remix-run/react"},{"path":"empty-module:react","kind":"import-statement","original":"react"},{"path":"empty-module:~/models/note.server","kind":"import-statement","original":"~/models/note.server"},{"path":"empty-module:~/session.server","kind":"import-statement","original":"~/session.server"},{"path":"empty-module:react/jsx-dev-runtime","kind":"import-statement","original":"react/jsx-dev-runtime"}],"format":"esm"},"app/utils.js":{"bytes":1752,"imports":[{"path":"empty-module:@remix-run/react","kind":"import-statement","original":"@remix-run/react"},{"path":"empty-module:react","kind":"import-statement","original":"react"}],"format":"esm"},"app/routes/_index.jsx":{"bytes":6377,"imports":[{"path":"empty-module:@remix-run/react","kind":"import-statement","original":"@remix-run/react"},{"path":"app/utils.js","kind":"import-statement","original":"~/utils"},{"path":"empty-module:react/jsx-dev-runtime","kind":"import-statement","original":"react/jsx-dev-runtime"}],"format":"esm"},"app/routes/logout.jsx":{"bytes":201,"imports":[{"path":"empty-module:@remix-run/node","kind":"import-statement","original":"@remix-run/node"},{"path":"empty-module:~/session.server","kind":"import-statement","original":"~/session.server"}],"format":"esm"},"empty-module:~/models/user.server":{"bytes":20,"imports":[],"format":"cjs"},"app/routes/login.jsx":{"bytes":5375,"imports":[{"path":"empty-module:@remix-run/node","kind":"import-statement","original":"@remix-run/node"},{"path":"empty-module:@remix-run/react","kind":"import-statement","original":"@remix-run/react"},{"path":"empty-module:react","kind":"import-statement","original":"react"},{"path":"empty-module:~/models/user.server","kind":"import-statement","original":"~/models/user.server"},{"path":"empty-module:~/session.server","kind":"import-statement","original":"~/session.server"},{"path":"app/utils.js","kind":"import-statement","original":"~/utils"},{"path":"empty-module:react/jsx-dev-runtime","kind":"import-statement","original":"react/jsx-dev-runtime"}],"format":"esm"},"app/routes/notes.jsx":{"bytes":2048,"imports":[{"path":"empty-module:@remix-run/node","kind":"import-statement","original":"@remix-run/node"},{"path":"empty-module:@remix-run/react","kind":"import-statement","original":"@remix-run/react"},{"path":"empty-module:~/models/note.server","kind":"import-statement","original":"~/models/note.server"},{"path":"empty-module:~/session.server","kind":"import-statement","original":"~/session.server"},{"path":"app/utils.js","kind":"import-statement","original":"~/utils"},{"path":"empty-module:react/jsx-dev-runtime","kind":"import-statement","original":"react/jsx-dev-runtime"}],"format":"esm"},"app/routes/join.jsx":{"bytes":4957,"imports":[{"path":"empty-module:@remix-run/node","kind":"import-statement","original":"@remix-run/node"},{"path":"empty-module:@remix-run/react","kind":"import-statement","original":"@remix-run/react"},{"path":"empty-module:react","kind":"import-statement","original":"react"},{"path":"empty-module:~/models/user.server","kind":"import-statement","original":"~/models/user.server"},{"path":"empty-module:~/session.server","kind":"import-statement","original":"~/session.server"},{"path":"app/utils.js","kind":"import-statement","original":"~/utils"},{"path":"empty-module:react/jsx-dev-runtime","kind":"import-statement","original":"react/jsx-dev-runtime"}],"format":"esm"},"css-bundle-entry-module:__remix_cssBundleEntryModule__":{"bytes":561,"imports":[{"path":"app/entry.client.jsx","kind":"import-statement","original":"/Users/pavan/Desktop/remix-app/app/entry.client.jsx"},{"path":"app/root.jsx","kind":"import-statement","original":"./root.jsx"},{"path":"app/routes/notes.$noteId.jsx","kind":"import-statement","original":"./routes/notes.$noteId.jsx"},{"path":"app/routes/notes._index.jsx","kind":"import-statement","original":"./routes/notes._index.jsx"},{"path":"app/routes/healthcheck.jsx","kind":"import-statement","original":"./routes/healthcheck.jsx"},{"path":"app/routes/notes.new.jsx","kind":"import-statement","original":"./routes/notes.new.jsx"},{"path":"app/routes/_index.jsx","kind":"import-statement","original":"./routes/_index.jsx"},{"path":"app/routes/logout.jsx","kind":"import-statement","original":"./routes/logout.jsx"},{"path":"app/routes/login.jsx","kind":"import-statement","original":"./routes/login.jsx"},{"path":"app/routes/notes.jsx","kind":"import-statement","original":"./routes/notes.jsx"},{"path":"app/routes/join.jsx","kind":"import-statement","original":"./routes/join.jsx"}],"format":"esm"}},"outputs":{"public/build/_assets/tailwind-QZDS6A7W.css":{"imports":[],"exports":[],"inputs":{"app/tailwind.css":{"bytesInOutput":15532}},"bytes":15532},"public/build/css-bundle-X5YBMC6V.js.map":{"imports":[],"exports":[],"inputs":{},"bytes":51523},"public/build/css-bundle-X5YBMC6V.js":{"imports":[{"path":"public/build/_assets/tailwind-QZDS6A7W.css","kind":"file-loader"}],"exports":["entryClient","route0","route1","route2","route3","route4","route5","route6","route7","route8","route9"],"entryPoint":"css-bundle-entry-module:__remix_cssBundleEntryModule__","inputs":{"empty-module:@remix-run/react":{"bytesInOutput":119},"empty-module:react":{"bytesInOutput":109},"empty-module:react-dom/client":{"bytesInOutput":120},"empty-module:react/jsx-dev-runtime":{"bytesInOutput":134},"empty-module:@remix-run/css-bundle":{"bytesInOutput":129},"empty-module:@remix-run/node":{"bytesInOutput":117},"empty-module:~/session.server":{"bytesInOutput":121},"empty-module:~/models/note.server":{"bytesInOutput":122},"empty-module:~/db.server":{"bytesInOutput":111},"empty-module:~/models/user.server":{"bytesInOutput":122},"app/entry.client.jsx":{"bytesInOutput":741},"css-bundle-entry-module:__remix_cssBundleEntryModule__":{"bytesInOutput":0},"app/root.jsx":{"bytesInOutput":2988},"app/tailwind.css":{"bytesInOutput":63},"app/routes/notes.$noteId.jsx":{"bytesInOutput":3877},"node_modules/tiny-invariant/dist/esm/tiny-invariant.js":{"bytesInOutput":364},"app/routes/notes._index.jsx":{"bytesInOutput":782},"app/routes/healthcheck.jsx":{"bytesInOutput":694},"app/routes/notes.new.jsx":{"bytesInOutput":6799},"app/routes/_index.jsx":{"bytesInOutput":10009},"app/utils.js":{"bytesInOutput":1247},"app/routes/logout.jsx":{"bytesInOutput":333},"app/routes/login.jsx":{"bytesInOutput":10104},"app/routes/notes.jsx":{"bytesInOutput":5232},"app/routes/join.jsx":{"bytesInOutput":8955}},"bytes":56044}}}